pcap2http/__init__.py
pcap2http/pcap2http.py
pcap2http/proxy.py
pcap2http/pcapparsermod/__init__.py
pcap2http/pcapparsermod/__main__.py
pcap2http/pcapparsermod/config.py
pcap2http/pcapparsermod/constant.py
pcap2http/pcapparsermod/httpparser.py
pcap2http/pcapparsermod/link_layer.py
pcap2http/pcapparsermod/packet_counter.py
pcap2http/pcapparsermod/packet_parser.py
pcap2http/pcapparsermod/parse_pcap.py
pcap2http/pcapparsermod/pcap.py
pcap2http/pcapparsermod/pcapng.py
pcap2http/pcapparsermod/printer.py
pcap2http/pcapparsermod/reader.py
pcap2http/pcapparsermod/save_to_storage.py
pcap2http/pcapparsermod/six.py
pcap2http/pcapparsermod/utils.py
pcap2http-1.1.dist-info/DESCRIPTION.rst
pcap2http-1.1.dist-info/METADATA
pcap2http-1.1.dist-info/RECORD
pcap2http-1.1.dist-info/WHEEL
pcap2http-1.1.dist-info/metadata.json
pcap2http-1.1.dist-info/top_level.txt
