Metadata-Version: 2.0
Name: pcap2http
Version: 1.1
Summary: Parse pcap file with python and watch sites in a browser or a file system
Home-page: https://github.com/ex0dus-cpp/pcap2http
Author: ex0dus-cpp
Author-email: UNKNOWN
License: UNKNOWN
Keywords: pcap http
Platform: UNKNOWN
